babore_dummy.py
babore/__init__.py
babore.egg-info/PKG-INFO
babore.egg-info/SOURCES.txt
babore.egg-info/dependency_links.txt
babore.egg-info/top_level.txt