Metadata-Version: 1.1
Name: babore
Version: 0.0.1
Summary: BombSquad framework for modding servers
Home-page: https://github.com/Ms-company-BombSquad/babore
Author: Ivan Ms
Author-email: ivanms.ept@gmail.com
License: BSD-3-Clause license
Download-URL: https://github.com/Ms-company-BombSquad/babore/archive/v0.0.1.zip
Platform: UNKNOWN
